[{"Code":"en","Title":"Vietnam","Slug":"payouts-coverage-vietnam","ContentType":2,"Content":"<div data-type=\"table-content\"><table width=\"948\" class=\"editor360-table\" borderstyle=\"solid\" style=\"max-width:948px;width:948px;\"><colgroup><col style=\"width:316px;\"><col style=\"width:316px;\"><col style=\"width:316px;\"></colgroup><tbody><tr><th colspan=\"1\" rowspan=\"1\" colwidth=\"316\"><p data-block-id=\"a46799c5-79e7-4b42-bf44-04ebb1f006a9\">Payout Rail</p></th><th colspan=\"1\" rowspan=\"1\" colwidth=\"316\"><p data-block-id=\"1bbe6011-d342-488d-8032-2f1c5b9094c7\">NAPAS</p></th><th colspan=\"1\" rowspan=\"1\" colwidth=\"316\"><p data-block-id=\"2e324178-d166-45d1-b09e-59b8bdf517fe\">CITAD*</p></th></tr><tr><td colspan=\"1\" rowspan=\"1\" colwidth=\"316\"><p data-block-id=\"7b54e4a3-e12a-41a7-b779-eb458513d305\">Supported Currencies</p></td><td colspan=\"1\" rowspan=\"1\" colwidth=\"316\"><p data-block-id=\"ee3cc23e-f3fe-472e-9314-0bb21cba57f9\">VND</p></td><td colspan=\"1\" rowspan=\"1\" colwidth=\"316\"><p data-block-id=\"6a90da83-e804-430e-b19b-d5235ec21e62\">VND</p></td></tr><tr><td colspan=\"1\" rowspan=\"1\" colwidth=\"316\"><p data-block-id=\"ca23e1b3-66d8-4b3d-bfa5-46d250a8e7ac\">Estimated Time of Arrival</p></td><td colspan=\"1\" rowspan=\"1\" colwidth=\"316\"><p data-block-id=\"2a7800a0-08a0-4a4e-b853-a8e9ab33ecf7\">15 minutes</p></td><td colspan=\"1\" rowspan=\"1\" colwidth=\"316\"><p data-block-id=\"b8607f84-a141-4900-9b91-843b1dbb4246\">Same Day</p></td></tr><tr><td colspan=\"1\" rowspan=\"1\" colwidth=\"316\"><p data-block-id=\"aaa3529a-0e88-40ad-94bc-2e2618fd5094\">Cut-off Time</p></td><td colspan=\"1\" rowspan=\"1\" colwidth=\"316\"><p data-block-id=\"3f1f6a57-7f89-45c2-839d-a8d96f406ac1\">N/A</p></td><td colspan=\"1\" rowspan=\"1\" colwidth=\"316\"><p data-block-id=\"aa1cbfe7-5805-45f2-b0f2-b6820707efa4\">14:00 GMT+7</p></td></tr><tr><td colspan=\"1\" rowspan=\"1\" colwidth=\"316\"><p data-block-id=\"0dc221e0-31e5-40c6-b34e-cfb4561ce9b0\">Transaction Limit</p></td><td colspan=\"1\" rowspan=\"1\" colwidth=\"316\"><p data-block-id=\"a51c7e2a-9356-4752-aefe-3d424e870aa7\">299,000,000</p></td><td colspan=\"1\" rowspan=\"1\" colwidth=\"316\"><p data-block-id=\"c7cc5402-1eec-4908-a809-08c7de65390f\">Unlimited</p></td></tr><tr><td colspan=\"1\" rowspan=\"1\" colwidth=\"316\"><p data-block-id=\"15da2347-b5e2-459c-81bf-c1c2efadc5e9\">Description Support</p></td><td colspan=\"1\" rowspan=\"1\" colwidth=\"316\"><p data-block-id=\"83ec00f0-fac3-460d-b550-3f7efe973029\">No</p></td><td colspan=\"1\" rowspan=\"1\" colwidth=\"316\"><p data-block-id=\"22668692-b6e0-4255-acba-8fea1e808ee2\">No</p></td></tr><tr><td colspan=\"1\" rowspan=\"1\" colwidth=\"316\"><p data-block-id=\"e6aa451a-2f43-4e3a-ae85-f5b8184a1495\">Supported Use Case</p></td><td colspan=\"1\" rowspan=\"1\" colwidth=\"316\"><p data-block-id=\"0664b24b-fd31-476e-a5b3-8f4045eeccb7\">Payout, Cross-Border Payout, Payout Link</p></td><td colspan=\"1\" rowspan=\"1\" colwidth=\"316\"><p data-block-id=\"ea29dea1-35c2-42b2-be02-5988f38d594c\">Payout, Cross-Border Payout, Payout Link</p></td></tr></tbody></table></div><p data-block-id=\"6e7615e0-9fa8-4682-906a-f2dbf515ba66\"><em>*Require activation. Contact help@xendit.co to activate.</em></p><h2 data-block-id=\"7ae25833-1a45-4534-8566-fc8d06501a1e\">Channel codes</h2><p data-block-id=\"1ff5713a-e672-4fa4-af2a-f5a48571b5fc\">Learn the different payout destinations that we support along with its destination-specific information in the table below:</p><p data-block-id=\"8af27fed-1dcd-416c-accd-ecef8c9cde3f\"><iframe src=\"https://airtable.com/embed/appYc7UnQq5CmKe0G/shrKTJKY9DD45nq2i?viewControls=on\" frameborder=\"0\" allowfullscreen=\"true\" allow=\"accelerometer; autoplay; clipboard-write; encrypted-media; gyroscope; picture-in-picture\" title=\"\" width=\"100%\" height=\"533\" onmousewheel=\"\" style=\"background:transparent;border:1px solid rgb(204, 204, 204);width:100%;height:533px;display:flex;margin-right:auto;\"></iframe></p><p data-block-id=\"165b5698-9657-4f6f-9219-6bf7ec19d301\"></p><h2 data-block-id=\"9ef535f3-07c9-462f-a7c4-7c6cadc264ac\">Required Values (For Cross Border Payouts)</h2><p data-block-id=\"e3e8f0c6-aaea-4305-b5f6-c729a4fea3f2\">As a prerequisite to creating a Cross Border Payout, you are required to send us the ultimate sender and recipient’s information. Learn the required information for the region to start sending payouts:</p><h3 data-block-id=\"f9c1c378-1df8-42bc-9910-5ab16f56b3b1\">Sender</h3><div data-type=\"table-content\"><table width=\"948\" class=\"editor360-table\" borderstyle=\"solid\" style=\"max-width:948px;width:948px;\"><colgroup><col style=\"width:316px;\"><col style=\"width:316px;\"><col style=\"width:316px;\"></colgroup><tbody><tr><th colspan=\"1\" rowspan=\"1\" colwidth=\"316\"><p data-block-id=\"2dea98bb-82b9-44d8-ba1e-1e72a2e60c65\">Field Parameter</p></th><th colspan=\"1\" rowspan=\"1\" colwidth=\"316\"><p data-block-id=\"96028edf-d5fe-4aa6-87e1-c48746354822\">Type</p></th><th colspan=\"1\" rowspan=\"1\" colwidth=\"316\"><p data-block-id=\"48b85d69-8943-419a-ab7a-39e0883e9173\">Description</p></th></tr><tr><td colspan=\"1\" rowspan=\"1\" colwidth=\"316\" style=\"vertical-align:middle;box-sizing:border-box;padding:10px;\"><p data-block-id=\"e4d8aa8e-f7f6-4f11-b61e-c014d82e3465\"><code>individual_detail.first_name</code></p></td><td colspan=\"1\" rowspan=\"1\" colwidth=\"316\"><p data-block-id=\"ccab8e1a-acd6-4f4b-8de6-02d58260793b\"><code>INDIVIDUAL</code></p></td><td colspan=\"1\" rowspan=\"1\" colwidth=\"316\" style=\"box-sizing:border-box;padding:10px;vertical-align:top;\"><p data-block-id=\"8a2d881d-a15f-48a6-ba74-318274878f60\">First name of sender</p></td></tr><tr><td colspan=\"1\" rowspan=\"1\" colwidth=\"316\" style=\"vertical-align:middle;box-sizing:border-box;padding:10px;\"><p data-block-id=\"8f6b72e4-3957-4586-b069-2995e01521ee\"><code>individual_detail.last_name</code></p></td><td colspan=\"1\" rowspan=\"1\" colwidth=\"316\"><p data-block-id=\"739ec33f-d34c-4e53-a5b1-1e1143fac00f\"><code>INDIVIDUAL</code></p></td><td colspan=\"1\" rowspan=\"1\" colwidth=\"316\" style=\"box-sizing:border-box;padding:10px;vertical-align:top;\"><p data-block-id=\"70683a7f-d642-4b5f-8a0b-05341a7cf49a\">Last name of sender</p></td></tr><tr><td colspan=\"1\" rowspan=\"1\" colwidth=\"316\"><p data-block-id=\"e94998e1-86de-493a-9c58-ec766926fca2\"><code>business_detail.business_name</code></p></td><td colspan=\"1\" rowspan=\"1\" colwidth=\"316\"><p data-block-id=\"4ac71789-7f47-4be4-86ae-c37e0701df84\"><code>BUSINESS</code></p></td><td colspan=\"1\" rowspan=\"1\" colwidth=\"316\" style=\"box-sizing:border-box;padding:10px;vertical-align:top;\"><p data-block-id=\"d307563d-5bd4-4cf3-b814-a8fc2e35b9d1\">Full registered name of sender</p></td></tr><tr><td colspan=\"1\" rowspan=\"1\" colwidth=\"316\"><p data-block-id=\"mji3ftbu-26v9ls-011\"><code>business_detail.business_domicile</code></p></td><td colspan=\"1\" rowspan=\"1\" colwidth=\"316\"><p data-block-id=\"mji3g06n-lxin1c-013\"><code>BUSINESS</code></p></td><td colspan=\"1\" rowspan=\"1\" colwidth=\"316\" style=\"box-sizing:border-box;padding:10px;vertical-align:top;\"><p data-block-id=\"mji3kxn7-vsx4o9-045\">Full address of sender</p></td></tr><tr><td colspan=\"1\" rowspan=\"1\" colwidth=\"316\"><p data-block-id=\"mji380qf-gbg74n-003\"><code>addresses.country</code></p></td><td colspan=\"1\" rowspan=\"1\" colwidth=\"316\"><p data-block-id=\"mji385bz-5p7g4u-004\">Any</p></td><td colspan=\"1\" rowspan=\"1\" colwidth=\"316\" style=\"box-sizing:border-box;padding:10px;vertical-align:top;\"><p data-block-id=\"mji3kxn7-d5999a-046\">Country address of sender</p></td></tr><tr><td colspan=\"1\" rowspan=\"1\" colwidth=\"316\"><p data-block-id=\"mji3gbg2-d18w1p-014\"><code>addresses.province_state</code></p></td><td colspan=\"1\" rowspan=\"1\" colwidth=\"316\"><p data-block-id=\"mji3k138-pg80bi-020\"><code>BUSINESS</code></p></td><td colspan=\"1\" rowspan=\"1\" colwidth=\"316\" style=\"box-sizing:border-box;padding:10px;vertical-align:top;\"><p data-block-id=\"mji3kxn8-13cvvh-047\">Province/State address of sender</p></td></tr><tr><td colspan=\"1\" rowspan=\"1\" colwidth=\"316\"><p data-block-id=\"mji3gfn4-all5f7-016\"><code>addresses.city</code></p></td><td colspan=\"1\" rowspan=\"1\" colwidth=\"316\"><p data-block-id=\"mji3k2os-nzikdl-021\"><code>BUSINESS</code></p></td><td colspan=\"1\" rowspan=\"1\" colwidth=\"316\" style=\"box-sizing:border-box;padding:10px;vertical-align:top;\"><p data-block-id=\"mji3kxn8-12e2l8-048\">City address of sender</p></td></tr><tr><td colspan=\"1\" rowspan=\"1\" colwidth=\"316\"><p data-block-id=\"mji3ggh4-l80q16-018\"><code>addresses.street_line1</code></p></td><td colspan=\"1\" rowspan=\"1\" colwidth=\"316\"><p data-block-id=\"mji3k457-m6ayik-022\"><code>BUSINESS</code></p></td><td colspan=\"1\" rowspan=\"1\" colwidth=\"316\" style=\"box-sizing:border-box;padding:10px;vertical-align:top;\"><p data-block-id=\"mji3kxn8-ql6jac-049\">Full address of sender</p></td></tr></tbody></table></div><p data-block-id=\"1491a0dd-d239-4440-a9e0-785b37ffc0b3\"></p><h3 data-block-id=\"a94aeee5-d7ca-41d9-832a-c26744f93aaf\">Recipient</h3><div data-type=\"table-content\"><table width=\"948\" class=\"editor360-table\" borderstyle=\"solid\" style=\"max-width:948px;width:948px;\"><colgroup><col style=\"width:316px;\"><col style=\"width:316px;\"><col style=\"width:316px;\"></colgroup><tbody><tr><th colspan=\"1\" rowspan=\"1\" colwidth=\"316\"><p data-block-id=\"42269971-6ddd-41de-b872-2d1d7dfe8a5a\">Field Parameter</p></th><th colspan=\"1\" rowspan=\"1\" colwidth=\"316\"><p data-block-id=\"b58f2415-8361-45f5-a06d-e2267c81f78c\">Type</p></th><th colspan=\"1\" rowspan=\"1\" colwidth=\"316\"><p data-block-id=\"0595f7e6-463b-42de-8000-5cf48d44ac2a\">Description</p></th></tr><tr><td colspan=\"1\" rowspan=\"1\" colwidth=\"316\" style=\"vertical-align:middle;box-sizing:border-box;padding:10px;\"><p data-block-id=\"mji3r0cy-ox8azr-075\"><code>individual_detail.first_name</code></p></td><td colspan=\"1\" rowspan=\"1\" colwidth=\"316\"><p data-block-id=\"5e3de2cf-74eb-45ed-a2e5-54136513ab92\"><code>INDIVIDUAL</code></p></td><td colspan=\"1\" rowspan=\"1\" colwidth=\"316\" style=\"box-sizing:border-box;padding:10px;vertical-align:top;\"><p data-block-id=\"d339a321-3d87-4381-abd2-d64364126a94\">First name of recipient</p></td></tr><tr><td colspan=\"1\" rowspan=\"1\" colwidth=\"316\" style=\"vertical-align:middle;box-sizing:border-box;padding:10px;\"><p data-block-id=\"mji3r0cy-b5cbyx-076\"><code>individual_detail.last_name</code></p></td><td colspan=\"1\" rowspan=\"1\" colwidth=\"316\"><p data-block-id=\"e531b009-eef3-44da-ad1e-f61dde6571eb\"><code>INDIVIDUAL</code></p></td><td colspan=\"1\" rowspan=\"1\" colwidth=\"316\" style=\"box-sizing:border-box;padding:10px;vertical-align:top;\"><p data-block-id=\"179b7c54-f42a-491c-8a11-2585aa854342\">Last name of recipient</p></td></tr><tr><td colspan=\"1\" rowspan=\"1\" colwidth=\"316\"><p data-block-id=\"mji3r0cy-yz0wyi-077\"><code>business_detail.business_name</code></p></td><td colspan=\"1\" rowspan=\"1\" colwidth=\"316\"><p data-block-id=\"79a70831-46d4-4886-a7a1-09c78ba2f6c2\"><code>BUSINESS</code></p></td><td colspan=\"1\" rowspan=\"1\" colwidth=\"316\" style=\"box-sizing:border-box;padding:10px;vertical-align:top;\"><p data-block-id=\"20c947e9-b84f-4391-a8a2-488ad68945c1\">Full registered name of recipient</p></td></tr><tr><td colspan=\"1\" rowspan=\"1\" colwidth=\"316\" style=\"box-sizing:border-box;padding:10px;vertical-align:top;\"><p data-block-id=\"mji3l6cs-asiltv-056\"><code>identity_accounts.type</code></p></td><td colspan=\"1\" rowspan=\"1\" colwidth=\"316\" style=\"box-sizing:border-box;padding:10px;vertical-align:top;\"><p data-block-id=\"mji3l6cs-krxkze-057\">Any</p></td><td colspan=\"1\" rowspan=\"1\" colwidth=\"316\" style=\"box-sizing:border-box;padding:10px;vertical-align:top;\"><p data-block-id=\"mji3l6ct-m5fd2n-058\">Account type of the recipient’s account</p></td></tr><tr><td colspan=\"1\" rowspan=\"1\" colwidth=\"316\" style=\"box-sizing:border-box;padding:10px;vertical-align:top;\"><p data-block-id=\"mji3l6ct-2h1wlg-059\"><code>identity_accounts.company</code></p></td><td colspan=\"1\" rowspan=\"1\" colwidth=\"316\" style=\"box-sizing:border-box;padding:10px;vertical-align:top;\"><p data-block-id=\"mji3l6ct-ergtft-060\">Any</p></td><td colspan=\"1\" rowspan=\"1\" colwidth=\"316\" style=\"box-sizing:border-box;padding:10px;vertical-align:top;\"><p data-block-id=\"mji3l6ct-nmxpsv-061\">Channel code of the recipient’s account</p></td></tr><tr><td colspan=\"1\" rowspan=\"1\" colwidth=\"316\"><p data-block-id=\"mji3lfez-feh9m8-070\"><code>identity_accounts.country</code></p></td><td colspan=\"1\" rowspan=\"1\" colwidth=\"316\" style=\"box-sizing:border-box;padding:10px;vertical-align:top;\"><p data-block-id=\"mji3lhzy-ib1e3n-071\">Any</p></td><td colspan=\"1\" rowspan=\"1\" colwidth=\"316\" style=\"box-sizing:border-box;padding:10px;vertical-align:top;\"><p data-block-id=\"mji3lji2-g7qqoi-072\">Issuing country of the recipient’s account</p></td></tr><tr><td colspan=\"1\" rowspan=\"1\" colwidth=\"316\" style=\"box-sizing:border-box;padding:10px;vertical-align:top;\"><p data-block-id=\"mji3l6ct-ts688n-062\"><code>identity_accounts.properties.account_number</code></p></td><td colspan=\"1\" rowspan=\"1\" colwidth=\"316\" style=\"box-sizing:border-box;padding:10px;vertical-align:top;\"><p data-block-id=\"mji3l6cu-fwbml7-063\">Any</p></td><td colspan=\"1\" rowspan=\"1\" colwidth=\"316\" style=\"box-sizing:border-box;padding:10px;vertical-align:top;\"><p data-block-id=\"mji3l6cu-bj5nfn-064\">Account number of the recipient’s account</p></td></tr><tr><td colspan=\"1\" rowspan=\"1\" colwidth=\"316\"><p data-block-id=\"mji3l6cu-dvi66w-065\"><code>identity_accounts.properties.account_holder_name</code></p></td><td colspan=\"1\" rowspan=\"1\" colwidth=\"316\" style=\"box-sizing:border-box;padding:10px;vertical-align:top;\"><p data-block-id=\"mji3l6cu-xuzcdc-066\">Any</p></td><td colspan=\"1\" rowspan=\"1\" colwidth=\"316\"><p data-block-id=\"mji3l6cu-vm3o32-067\">Account holder name of the recipient’s account</p></td></tr></tbody></table></div><p data-block-id=\"a5f4e0e1-5934-430e-826b-509b4142bcf3\"></p>","SeoTitle":"Vietnam","Description":null},{"Code":"id","Title":"Vietnam","Slug":"payouts-vietnam","ContentType":2,"Content":"<div data-type=\"table-content\"><table width=\"948\" class=\"editor360-table\" borderstyle=\"solid\" style=\"max-width:948px;width:948px;\"><colgroup><col style=\"width:316px;\"><col style=\"width:316px;\"><col style=\"width:316px;\"></colgroup><tbody><tr><th colspan=\"1\" rowspan=\"1\" colwidth=\"316\"><p data-block-id=\"mcc9iccv-785gw5-786\">Payout Rail</p></th><th colspan=\"1\" rowspan=\"1\" colwidth=\"316\"><p data-block-id=\"mcc9gvv0-68adz5-720\">NAPAS</p></th><th colspan=\"1\" rowspan=\"1\" colwidth=\"316\"><p data-block-id=\"mcc9gvv0-i3864s-721\">CITAD*</p></th></tr><tr><td colspan=\"1\" rowspan=\"1\" colwidth=\"316\"><p data-block-id=\"mcc9iccv-jde55c-787\">Supported Currencies</p></td><td colspan=\"1\" rowspan=\"1\" colwidth=\"316\"><p data-block-id=\"mcc9gvv1-s9kqay-723\">VND</p></td><td colspan=\"1\" rowspan=\"1\" colwidth=\"316\"><p data-block-id=\"mcc9gvv1-483c3v-724\">VND</p></td></tr><tr><td colspan=\"1\" rowspan=\"1\" colwidth=\"316\"><p data-block-id=\"mcc9iccw-hmrf7e-788\">Estimated Time of Arrival</p></td><td colspan=\"1\" rowspan=\"1\" colwidth=\"316\"><p data-block-id=\"mcc9gvv1-5q6nr2-726\">15 menit</p></td><td colspan=\"1\" rowspan=\"1\" colwidth=\"316\"><p data-block-id=\"mcc9gvv1-85c3d8-727\">Hari yang sama</p></td></tr><tr><td colspan=\"1\" rowspan=\"1\" colwidth=\"316\"><p data-block-id=\"mcc9iccw-n10so8-789\">Cut-off Time</p></td><td colspan=\"1\" rowspan=\"1\" colwidth=\"316\"><p data-block-id=\"mcc9gvv2-vplrmp-729\">N/A</p></td><td colspan=\"1\" rowspan=\"1\" colwidth=\"316\"><p data-block-id=\"mcc9gvv2-zhrnm8-730\">14:00 GMT+7</p></td></tr><tr><td colspan=\"1\" rowspan=\"1\" colwidth=\"316\"><p data-block-id=\"mcc9iccw-oguw2c-790\">Transaction Limit</p></td><td colspan=\"1\" rowspan=\"1\" colwidth=\"316\"><p data-block-id=\"mcc9gvv2-ceunpr-732\">250,000,000</p></td><td colspan=\"1\" rowspan=\"1\" colwidth=\"316\"><p data-block-id=\"mcc9gvv2-dbuymy-733\">Unlimited</p></td></tr><tr><td colspan=\"1\" rowspan=\"1\" colwidth=\"316\"><p data-block-id=\"mcc9iccx-5arsho-791\">Description Support</p></td><td colspan=\"1\" rowspan=\"1\" colwidth=\"316\"><p data-block-id=\"mcc9gvv3-wldolm-735\">Tidak</p></td><td colspan=\"1\" rowspan=\"1\" colwidth=\"316\"><p data-block-id=\"mcc9gvv3-54mbx8-736\">Tidak</p></td></tr><tr><td colspan=\"1\" rowspan=\"1\" colwidth=\"316\"><p data-block-id=\"mcc9iccx-17pfdy-792\">Supported Use Case</p></td><td colspan=\"1\" rowspan=\"1\" colwidth=\"316\"><p data-block-id=\"mcc9gvv3-iriwrr-738\">Payout, Cross-Border Payout, Payout Link</p></td><td colspan=\"1\" rowspan=\"1\" colwidth=\"316\"><p data-block-id=\"mcc9gvv3-rdp9aa-739\">Payout, Cross-Border Payout, Payout Link</p></td></tr></tbody></table></div><p data-block-id=\"mcc9gvv3-rw0naw-740\"><em>*Memerlukan aktivasi. Hubungi help@xendit.co untuk mengaktifkan.</em></p><h2 data-block-id=\"mcc9gvv3-k285lu-741\">Kode channel</h2><p data-block-id=\"mcc9gvv3-3dgs0v-742\">Pelajari berbagai tujuan pembayaran yang kami dukung bersama dengan informasi khusus destinasinya dalam tabel di bawah ini:</p><p data-block-id=\"mcc9gvv4-2mbnzh-743\"><iframe src=\"https://airtable.com/embed/appYc7UnQq5CmKe0G/shrKTJKY9DD45nq2i?viewControls=on\" frameborder=\"0\" allowfullscreen=\"true\" allow=\"accelerometer; autoplay; clipboard-write; encrypted-media; gyroscope; picture-in-picture\" title=\"\" style=\"background:transparent;border:1px solid #ccc;width:100%;height:533px;display:flex;margin-right:auto;\" width=\"100%\" height=\"533\" onmousewheel=\"\"></iframe></p><h2 dir=\"ltr\" data-block-id=\"mcc9hluo-exbrde-784\">Value yang diperlukan Cross-Border Payouts</h2><p data-block-id=\"mcc9gvv4-ih8pm0-746\">Sebagai prasyarat untuk membuat Cross-Border Payoutss, Anda diminta untuk mengirimkan informasi pengirim dan penerima utama kepada kami. Pelajari informasi yang diperlukan bagi wilayah untuk mulai mengirim payout:</p><h3 data-block-id=\"mcc9gvv4-9ctlov-747\">Pengirim</h3><div data-type=\"table-content\"><table width=\"948\" class=\"editor360-table\" borderstyle=\"solid\" style=\"max-width:948px;width:948px;\"><colgroup><col style=\"width:316px;\"><col style=\"width:316px;\"><col style=\"width:316px;\"></colgroup><tbody><tr><th colspan=\"1\" rowspan=\"1\" colwidth=\"316\"><p data-block-id=\"mcc9gvv4-kkym5e-748\">Parameter</p></th><th colspan=\"1\" rowspan=\"1\" colwidth=\"316\"><p data-block-id=\"mcc9gvv5-sgvs4c-749\">Jenis</p></th><th colspan=\"1\" rowspan=\"1\" colwidth=\"316\"><p data-block-id=\"mcc9gvv5-hx4kfi-750\">Deskripsi</p></th></tr><tr><td colspan=\"1\" rowspan=\"1\" colwidth=\"316\" style=\"vertical-align:middle;box-sizing:border-box;padding:10px;\"><p data-block-id=\"mcc9gvv5-9z4vqz-751\"><code>first_name</code></p></td><td colspan=\"1\" rowspan=\"1\" colwidth=\"316\"><p data-block-id=\"mcc9gvv5-8fluzr-752\"><code>INDIVIDUAL</code></p></td><td colspan=\"1\" rowspan=\"1\" colwidth=\"316\" style=\"box-sizing:border-box;padding:10px;vertical-align:top;\"><p data-block-id=\"mcc9gvv5-5tdumz-753\">Nama depan pengirim</p></td></tr><tr><td colspan=\"1\" rowspan=\"1\" colwidth=\"316\" style=\"vertical-align:middle;box-sizing:border-box;padding:10px;\"><p data-block-id=\"mcc9gvv6-tpderw-754\"><code>last_name</code></p></td><td colspan=\"1\" rowspan=\"1\" colwidth=\"316\"><p data-block-id=\"mcc9gvv6-8z0ewq-755\"><code>INDIVIDUAL</code></p></td><td colspan=\"1\" rowspan=\"1\" colwidth=\"316\" style=\"box-sizing:border-box;padding:10px;vertical-align:top;\"><p data-block-id=\"mcc9gvv6-bryuvj-756\">Nama belakang pengirim</p></td></tr><tr><td colspan=\"1\" rowspan=\"1\" colwidth=\"316\"><p data-block-id=\"mcc9gvv6-5aay8b-757\"><code>business_name</code></p></td><td colspan=\"1\" rowspan=\"1\" colwidth=\"316\"><p data-block-id=\"mcc9gvv6-u9erci-758\"><code>BUSINESS</code></p></td><td colspan=\"1\" rowspan=\"1\" colwidth=\"316\" style=\"box-sizing:border-box;padding:10px;vertical-align:top;\"><p data-block-id=\"mcc9gvv7-efyv62-759\">Nama lengkap pengirim yang terdaftar</p></td></tr></tbody></table></div><p data-block-id=\"mcc9gvv7-pmseo8-760\"></p><h3 data-block-id=\"mcc9gvv7-qai27l-761\">Penerima</h3><div data-type=\"table-content\"><table width=\"948\" class=\"editor360-table\" borderstyle=\"solid\" style=\"max-width:948px;width:948px;\"><colgroup><col style=\"width:316px;\"><col style=\"width:316px;\"><col style=\"width:316px;\"></colgroup><tbody><tr><th colspan=\"1\" rowspan=\"1\" colwidth=\"316\"><p data-block-id=\"mcc9gvv7-spsgvd-762\">Parameter</p></th><th colspan=\"1\" rowspan=\"1\" colwidth=\"316\"><p data-block-id=\"mcc9gvv7-sc2m0o-763\">Jenis</p></th><th colspan=\"1\" rowspan=\"1\" colwidth=\"316\"><p data-block-id=\"mcc9gvv7-xcei8t-764\">Deskripsi</p></th></tr><tr><td colspan=\"1\" rowspan=\"1\" colwidth=\"316\" style=\"vertical-align:middle;box-sizing:border-box;padding:10px;\"><p data-block-id=\"mcc9gvv7-1m4csk-765\"><code>first_name</code></p></td><td colspan=\"1\" rowspan=\"1\" colwidth=\"316\"><p data-block-id=\"mcc9gvv8-4dhkll-766\"><code>INDIVIDUAL</code></p></td><td colspan=\"1\" rowspan=\"1\" colwidth=\"316\" style=\"box-sizing:border-box;padding:10px;vertical-align:top;\"><p data-block-id=\"mcc9gvv8-2eq5ko-767\">Nama depan penerima</p></td></tr><tr><td colspan=\"1\" rowspan=\"1\" colwidth=\"316\" style=\"vertical-align:middle;box-sizing:border-box;padding:10px;\"><p data-block-id=\"mcc9gvv8-g2sa4h-768\"><code>last_name</code></p></td><td colspan=\"1\" rowspan=\"1\" colwidth=\"316\"><p data-block-id=\"mcc9gvv8-hs1nzv-769\"><code>INDIVIDUAL</code></p></td><td colspan=\"1\" rowspan=\"1\" colwidth=\"316\" style=\"box-sizing:border-box;padding:10px;vertical-align:top;\"><p data-block-id=\"mcc9gvv8-ckn2ay-770\">Nama belakang penerima</p></td></tr><tr><td colspan=\"1\" rowspan=\"1\" colwidth=\"316\"><p data-block-id=\"mcc9gvv9-ug5hh5-771\"><code>business_name</code></p></td><td colspan=\"1\" rowspan=\"1\" colwidth=\"316\"><p data-block-id=\"mcc9gvv9-gxkat8-772\"><code>BUSINESS</code></p></td><td colspan=\"1\" rowspan=\"1\" colwidth=\"316\" style=\"box-sizing:border-box;padding:10px;vertical-align:top;\"><p data-block-id=\"mcc9gvv9-mi2ob4-773\">Nama lengkap penerima yang terdaftar</p></td></tr><tr><td colspan=\"1\" rowspan=\"1\" colwidth=\"316\" style=\"box-sizing:border-box;padding:10px;vertical-align:top;\"><p data-block-id=\"mcc9gvv9-x480qv-774\"><code>company</code></p></td><td colspan=\"1\" rowspan=\"1\" colwidth=\"316\" style=\"box-sizing:border-box;padding:10px;vertical-align:top;\"><p data-block-id=\"mcc9gvv9-l2p7zk-775\">Setiap</p></td><td colspan=\"1\" rowspan=\"1\" colwidth=\"316\" style=\"box-sizing:border-box;padding:10px;vertical-align:top;\"><p data-block-id=\"mcc9gvv9-ilgbcr-776\">Kode channel akun penerima</p></td></tr><tr><td colspan=\"1\" rowspan=\"1\" colwidth=\"316\" style=\"box-sizing:border-box;padding:10px;vertical-align:top;\"><p data-block-id=\"mcc9gvva-m3fvmn-777\"><code>account_number</code></p></td><td colspan=\"1\" rowspan=\"1\" colwidth=\"316\" style=\"box-sizing:border-box;padding:10px;vertical-align:top;\"><p data-block-id=\"mcc9gvva-jbsul2-778\">Setiap</p></td><td colspan=\"1\" rowspan=\"1\" colwidth=\"316\" style=\"box-sizing:border-box;padding:10px;vertical-align:top;\"><p data-block-id=\"mcc9gvva-iaa255-779\">Nomor rekening detail akun penerima</p></td></tr><tr><td colspan=\"1\" rowspan=\"1\" colwidth=\"316\"><p data-block-id=\"mcc9gvva-zt42q4-780\"><code>account_holder_name</code></p></td><td colspan=\"1\" rowspan=\"1\" colwidth=\"316\" style=\"box-sizing:border-box;padding:10px;vertical-align:top;\"><p data-block-id=\"mcc9gvva-7ugkc7-781\">Setiap</p></td><td colspan=\"1\" rowspan=\"1\" colwidth=\"316\"><p data-block-id=\"mcc9gvva-842tq6-782\">Nama pemegang akun detail akun penerima</p></td></tr></tbody></table></div><p data-block-id=\"mcc9gvva-2w8pzt-783\"></p>","SeoTitle":"Vietnam","Description":null},{"Code":"th","Title":"เวียดนาม","Slug":"vietnam-1","ContentType":2,"Content":"<style> p[data-block-id] {font-size:1rem;} ul li p[data-block-id] {margin-bottom: 0;} ul[data-type=\"taskList\"] li div p[data-block-id] {margin-bottom: 0;} ol li p[data-block-id] {margin-bottom: 0;} table tbody th p[data-block-id] { margin-bottom: 0;} blockquote p[data-block-id] {margin-bottom: 0 !important;}  p[data-block-id]:empty::after {content: \"\\00A0\";} </style><div data-type=\"table-content\"><table width=\"948\" class=\"editor360-table\" borderstyle=\"solid\" style=\"max-width:948px;width:948px;\"><colgroup><col style=\"width:316px;\"><col style=\"width:316px;\"><col style=\"width:316px;\"></colgroup><tbody><tr><th colspan=\"1\" rowspan=\"1\" colwidth=\"316\"><p data-block-id=\"a46799c5-79e7-4b42-bf44-04ebb1f006a9\">Payout Rail</p></th><th colspan=\"1\" rowspan=\"1\" colwidth=\"316\"><p data-block-id=\"1bbe6011-d342-488d-8032-2f1c5b9094c7\">NAPAS</p></th><th colspan=\"1\" rowspan=\"1\" colwidth=\"316\"><p data-block-id=\"2e324178-d166-45d1-b09e-59b8bdf517fe\">CITAD*</p></th></tr><tr><td colspan=\"1\" rowspan=\"1\" colwidth=\"316\"><p data-block-id=\"7b54e4a3-e12a-41a7-b779-eb458513d305\">สกุลเงินที่รองรับ</p></td><td colspan=\"1\" rowspan=\"1\" colwidth=\"316\"><p data-block-id=\"ee3cc23e-f3fe-472e-9314-0bb21cba57f9\">VND</p></td><td colspan=\"1\" rowspan=\"1\" colwidth=\"316\"><p data-block-id=\"6a90da83-e804-430e-b19b-d5235ec21e62\">VND</p></td></tr><tr><td colspan=\"1\" rowspan=\"1\" colwidth=\"316\"><p data-block-id=\"ca23e1b3-66d8-4b3d-bfa5-46d250a8e7ac\">เวลาถึงโดยประมาณ</p></td><td colspan=\"1\" rowspan=\"1\" colwidth=\"316\"><p data-block-id=\"2a7800a0-08a0-4a4e-b853-a8e9ab33ecf7\">15 นาที</p></td><td colspan=\"1\" rowspan=\"1\" colwidth=\"316\"><p data-block-id=\"b8607f84-a141-4900-9b91-843b1dbb4246\">ภายในวันเดียวกัน</p></td></tr><tr><td colspan=\"1\" rowspan=\"1\" colwidth=\"316\"><p data-block-id=\"aaa3529a-0e88-40ad-94bc-2e2618fd5094\">เวลาตัดยอด</p></td><td colspan=\"1\" rowspan=\"1\" colwidth=\"316\"><p data-block-id=\"3f1f6a57-7f89-45c2-839d-a8d96f406ac1\">N/A</p></td><td colspan=\"1\" rowspan=\"1\" colwidth=\"316\"><p data-block-id=\"aa1cbfe7-5805-45f2-b0f2-b6820707efa4\">14:00 GMT+7</p></td></tr><tr><td colspan=\"1\" rowspan=\"1\" colwidth=\"316\"><p data-block-id=\"0dc221e0-31e5-40c6-b34e-cfb4561ce9b0\">วงเงินทำรายการ</p></td><td colspan=\"1\" rowspan=\"1\" colwidth=\"316\"><p data-block-id=\"a51c7e2a-9356-4752-aefe-3d424e870aa7\">250,000,000</p></td><td colspan=\"1\" rowspan=\"1\" colwidth=\"316\"><p data-block-id=\"c7cc5402-1eec-4908-a809-08c7de65390f\">ไม่จำกัด</p></td></tr><tr><td colspan=\"1\" rowspan=\"1\" colwidth=\"316\"><p data-block-id=\"15da2347-b5e2-459c-81bf-c1c2efadc5e9\">รองรับคำอธิบาย</p></td><td colspan=\"1\" rowspan=\"1\" colwidth=\"316\"><p data-block-id=\"83ec00f0-fac3-460d-b550-3f7efe973029\">ไม่รองรับ</p></td><td colspan=\"1\" rowspan=\"1\" colwidth=\"316\"><p data-block-id=\"22668692-b6e0-4255-acba-8fea1e808ee2\">ไม่รองรับ</p></td></tr><tr><td colspan=\"1\" rowspan=\"1\" colwidth=\"316\"><p data-block-id=\"e6aa451a-2f43-4e3a-ae85-f5b8184a1495\">กรณีการใช้งานที่รองรับ</p></td><td colspan=\"1\" rowspan=\"1\" colwidth=\"316\"><p data-block-id=\"0664b24b-fd31-476e-a5b3-8f4045eeccb7\">Payout, Cross-Border Payout, Payout Link</p></td><td colspan=\"1\" rowspan=\"1\" colwidth=\"316\"><p data-block-id=\"ea29dea1-35c2-42b2-be02-5988f38d594c\">Payout, Cross-Border Payout, Payout Link</p></td></tr></tbody></table></div><p data-block-id=\"6e7615e0-9fa8-4682-906a-f2dbf515ba66\"><em>*ต้องเปิดใช้งาน ติดต่อ help@xendit.co เพื่อเปิดใช้งาน</em></p><h2 data-block-id=\"7ae25833-1a45-4534-8566-fc8d06501a1e\">Channel codes</h2><p data-block-id=\"1ff5713a-e672-4fa4-af2a-f5a48571b5fc\">ดูปลายทางการจ่ายเงินต่างๆ ที่เรารองรับ พร้อมข้อมูลเฉพาะของปลายทางนั้นๆ ได้ในตารางด้านล่าง:</p><p data-block-id=\"8af27fed-1dcd-416c-accd-ecef8c9cde3f\"><iframe src=\"https://airtable.com/embed/appYc7UnQq5CmKe0G/shrKTJKY9DD45nq2i?viewControls=on\" frameborder=\"0\" allowfullscreen=\"true\" allow=\"accelerometer; autoplay; clipboard-write; encrypted-media; gyroscope; picture-in-picture\" title style=\"background:transparent;border:1px solid #ccc;width:100%;height:533px;display:flex;margin-right:auto;\" width=\"100%\" height=\"533\" onmousewheel></iframe></p><p data-block-id=\"165b5698-9657-4f6f-9219-6bf7ec19d301\"></p><h2 data-block-id=\"9ef535f3-07c9-462f-a7c4-7c6cadc264ac\">ค่าที่จำเป็น (สำหรับการจ่ายเงินข้ามพรมแดน)</h2><p data-block-id=\"e3e8f0c6-aaea-4305-b5f6-c729a4fea3f2\">ในฐานะข้อกำหนดเบื้องต้นในการสร้าง Cross Border Payout คุณจะต้องส่งข้อมูลผู้ส่งและผู้รับปลายทางมาให้เรา ศึกษาข้อมูลที่จำเป็นสำหรับภูมิภาคเพื่อเริ่มส่ง Payout:</p><h3 data-block-id=\"f9c1c378-1df8-42bc-9910-5ab16f56b3b1\">ผู้ส่ง</h3><div data-type=\"table-content\"><table width=\"948\" class=\"editor360-table\" borderstyle=\"solid\" style=\"max-width:948px;width:948px;\"><colgroup><col style=\"width:316px;\"><col style=\"width:316px;\"><col style=\"width:316px;\"></colgroup><tbody><tr><th colspan=\"1\" rowspan=\"1\" colwidth=\"316\"><p data-block-id=\"2dea98bb-82b9-44d8-ba1e-1e72a2e60c65\">พารามิเตอร์ฟิลด์</p></th><th colspan=\"1\" rowspan=\"1\" colwidth=\"316\"><p data-block-id=\"96028edf-d5fe-4aa6-87e1-c48746354822\">ประเภท</p></th><th colspan=\"1\" rowspan=\"1\" colwidth=\"316\"><p data-block-id=\"48b85d69-8943-419a-ab7a-39e0883e9173\">คำอธิบาย</p></th></tr><tr><td colspan=\"1\" rowspan=\"1\" colwidth=\"316\" style=\"vertical-align:middle;box-sizing:border-box;padding:10px;\"><p data-block-id=\"e4d8aa8e-f7f6-4f11-b61e-c014d82e3465\"><code>first_name</code></p></td><td colspan=\"1\" rowspan=\"1\" colwidth=\"316\"><p data-block-id=\"ccab8e1a-acd6-4f4b-8de6-02d58260793b\"><code>INDIVIDUAL</code></p></td><td colspan=\"1\" rowspan=\"1\" colwidth=\"316\" style=\"box-sizing:border-box;padding:10px;vertical-align:top;\"><p data-block-id=\"8a2d881d-a15f-48a6-ba74-318274878f60\">ชื่อจริงของผู้ส่ง</p></td></tr><tr><td colspan=\"1\" rowspan=\"1\" colwidth=\"316\" style=\"vertical-align:middle;box-sizing:border-box;padding:10px;\"><p data-block-id=\"8f6b72e4-3957-4586-b069-2995e01521ee\"><code>last_name</code></p></td><td colspan=\"1\" rowspan=\"1\" colwidth=\"316\"><p data-block-id=\"739ec33f-d34c-4e53-a5b1-1e1143fac00f\"><code>INDIVIDUAL</code></p></td><td colspan=\"1\" rowspan=\"1\" colwidth=\"316\" style=\"box-sizing:border-box;padding:10px;vertical-align:top;\"><p data-block-id=\"70683a7f-d642-4b5f-8a0b-05341a7cf49a\">นามสกุลของผู้ส่ง</p></td></tr><tr><td colspan=\"1\" rowspan=\"1\" colwidth=\"316\"><p data-block-id=\"e94998e1-86de-493a-9c58-ec766926fca2\"><code>business_name</code></p></td><td colspan=\"1\" rowspan=\"1\" colwidth=\"316\"><p data-block-id=\"4ac71789-7f47-4be4-86ae-c37e0701df84\"><code>BUSINESS</code></p></td><td colspan=\"1\" rowspan=\"1\" colwidth=\"316\" style=\"box-sizing:border-box;padding:10px;vertical-align:top;\"><p data-block-id=\"d307563d-5bd4-4cf3-b814-a8fc2e35b9d1\">ชื่อจดทะเบียนเต็มของผู้ส่ง</p></td></tr></tbody></table></div><p data-block-id=\"1491a0dd-d239-4440-a9e0-785b37ffc0b3\"></p><h3 data-block-id=\"a94aeee5-d7ca-41d9-832a-c26744f93aaf\">ผู้รับ</h3><div data-type=\"table-content\"><table width=\"948\" class=\"editor360-table\" borderstyle=\"solid\" style=\"max-width:948px;width:948px;\"><colgroup><col style=\"width:316px;\"><col style=\"width:316px;\"><col style=\"width:316px;\"></colgroup><tbody><tr><th colspan=\"1\" rowspan=\"1\" colwidth=\"316\"><p data-block-id=\"42269971-6ddd-41de-b872-2d1d7dfe8a5a\">พารามิเตอร์ฟิลด์</p></th><th colspan=\"1\" rowspan=\"1\" colwidth=\"316\"><p data-block-id=\"b58f2415-8361-45f5-a06d-e2267c81f78c\">ประเภท</p></th><th colspan=\"1\" rowspan=\"1\" colwidth=\"316\"><p data-block-id=\"0595f7e6-463b-42de-8000-5cf48d44ac2a\">คำอธิบาย</p></th></tr><tr><td colspan=\"1\" rowspan=\"1\" colwidth=\"316\" style=\"vertical-align:middle;box-sizing:border-box;padding:10px;\"><p data-block-id=\"23b4dfad-06c8-467d-a369-5038efffa375\"><code>first_name</code></p></td><td colspan=\"1\" rowspan=\"1\" colwidth=\"316\"><p data-block-id=\"5e3de2cf-74eb-45ed-a2e5-54136513ab92\"><code>INDIVIDUAL</code></p></td><td colspan=\"1\" rowspan=\"1\" colwidth=\"316\" style=\"box-sizing:border-box;padding:10px;vertical-align:top;\"><p data-block-id=\"d339a321-3d87-4381-abd2-d64364126a94\">ชื่อจริงของผู้รับ</p></td></tr><tr><td colspan=\"1\" rowspan=\"1\" colwidth=\"316\" style=\"vertical-align:middle;box-sizing:border-box;padding:10px;\"><p data-block-id=\"ad5fd060-35db-4ccc-b3c6-352dcc8841b3\"><code>last_name</code></p></td><td colspan=\"1\" rowspan=\"1\" colwidth=\"316\"><p data-block-id=\"e531b009-eef3-44da-ad1e-f61dde6571eb\"><code>INDIVIDUAL</code></p></td><td colspan=\"1\" rowspan=\"1\" colwidth=\"316\" style=\"box-sizing:border-box;padding:10px;vertical-align:top;\"><p data-block-id=\"179b7c54-f42a-491c-8a11-2585aa854342\">นามสกุลของผู้รับ</p></td></tr><tr><td colspan=\"1\" rowspan=\"1\" colwidth=\"316\"><p data-block-id=\"e4b88d37-d942-47ad-ab65-1ad9c2f36b43\"><code>business_name</code></p></td><td colspan=\"1\" rowspan=\"1\" colwidth=\"316\"><p data-block-id=\"79a70831-46d4-4886-a7a1-09c78ba2f6c2\"><code>BUSINESS</code></p></td><td colspan=\"1\" rowspan=\"1\" colwidth=\"316\" style=\"box-sizing:border-box;padding:10px;vertical-align:top;\"><p data-block-id=\"20c947e9-b84f-4391-a8a2-488ad68945c1\">ชื่อจดทะเบียนเต็มของผู้รับ</p></td></tr><tr><td colspan=\"1\" rowspan=\"1\" colwidth=\"316\" style=\"box-sizing:border-box;padding:10px;vertical-align:top;\"><p data-block-id=\"bbed3e7b-c700-48c7-bbcb-5c0bee0fac29\"><code>company</code></p></td><td colspan=\"1\" rowspan=\"1\" colwidth=\"316\" style=\"box-sizing:border-box;padding:10px;vertical-align:top;\"><p data-block-id=\"1f0c7be5-df81-4d96-995c-0a983b371a6f\">Any</p></td><td colspan=\"1\" rowspan=\"1\" colwidth=\"316\" style=\"box-sizing:border-box;padding:10px;vertical-align:top;\"><p data-block-id=\"3587edb1-dcdb-4771-bb6f-97b91f2ed95e\">รหัสช่องทางของบัญชีผู้รับ</p></td></tr><tr><td colspan=\"1\" rowspan=\"1\" colwidth=\"316\" style=\"box-sizing:border-box;padding:10px;vertical-align:top;\"><p data-block-id=\"5e4d95d7-32b7-48f0-8294-16401b15fa48\"><code>account_number</code></p></td><td colspan=\"1\" rowspan=\"1\" colwidth=\"316\" style=\"box-sizing:border-box;padding:10px;vertical-align:top;\"><p data-block-id=\"96660eb6-1cc8-4571-aedc-820c49158ef1\">Any</p></td><td colspan=\"1\" rowspan=\"1\" colwidth=\"316\" style=\"box-sizing:border-box;padding:10px;vertical-align:top;\"><p data-block-id=\"df44dab6-aabb-4ec0-a931-5f422224244f\">หมายเลขบัญชีของรายละเอียดบัญชีผู้รับ</p></td></tr><tr><td colspan=\"1\" rowspan=\"1\" colwidth=\"316\"><p data-block-id=\"5ce0bfa2-25d9-4ed7-bfe2-3af9dc7a586d\"><code>account_holder_name</code></p></td><td colspan=\"1\" rowspan=\"1\" colwidth=\"316\" style=\"box-sizing:border-box;padding:10px;vertical-align:top;\"><p data-block-id=\"a4a2da7f-5976-4140-b265-f2e3d023f900\">Any</p></td><td colspan=\"1\" rowspan=\"1\" colwidth=\"316\"><p data-block-id=\"acbb63bf-dd76-4dff-8cba-7e43a253de2e\">ชื่อเจ้าของบัญชีของรายละเอียดบัญชีผู้รับ</p></td></tr></tbody></table></div><p data-block-id=\"a5f4e0e1-5934-430e-826b-509b4142bcf3\"></p>","SeoTitle":"เวียดนาม","Description":null},{"Code":"es-mx","Title":"Vietnam","Slug":"payouts-coverage-vietnam","ContentType":2,"Content":"<style> p[data-block-id] {font-size:1rem;} ul li p[data-block-id] {margin-bottom: 0;} ul[data-type=\"taskList\"] li div p[data-block-id] {margin-bottom: 0;} ol li p[data-block-id] {margin-bottom: 0;} table tbody th p[data-block-id] { margin-bottom: 0;} blockquote p[data-block-id] {margin-bottom: 0 !important;}  p[data-block-id]:empty::after {content: \"\\00A0\";} </style><div data-type=\"table-content\"><table width=\"948\" class=\"editor360-table\" borderstyle=\"solid\" style=\"max-width:948px;width:948px;\"><colgroup><col style=\"width:316px;\"><col style=\"width:316px;\"><col style=\"width:316px;\"></colgroup><tbody><tr><th colspan=\"1\" rowspan=\"1\" colwidth=\"316\"><p data-block-id=\"a46799c5-79e7-4b42-bf44-04ebb1f006a9\">Rail de Payout</p></th><th colspan=\"1\" rowspan=\"1\" colwidth=\"316\"><p data-block-id=\"1bbe6011-d342-488d-8032-2f1c5b9094c7\">NAPAS</p></th><th colspan=\"1\" rowspan=\"1\" colwidth=\"316\"><p data-block-id=\"2e324178-d166-45d1-b09e-59b8bdf517fe\">CITAD*</p></th></tr><tr><td colspan=\"1\" rowspan=\"1\" colwidth=\"316\"><p data-block-id=\"7b54e4a3-e12a-41a7-b779-eb458513d305\">Monedas Compatibles</p></td><td colspan=\"1\" rowspan=\"1\" colwidth=\"316\"><p data-block-id=\"ee3cc23e-f3fe-472e-9314-0bb21cba57f9\">VND</p></td><td colspan=\"1\" rowspan=\"1\" colwidth=\"316\"><p data-block-id=\"6a90da83-e804-430e-b19b-d5235ec21e62\">VND</p></td></tr><tr><td colspan=\"1\" rowspan=\"1\" colwidth=\"316\"><p data-block-id=\"ca23e1b3-66d8-4b3d-bfa5-46d250a8e7ac\">Tiempo Estimado de Llegada</p></td><td colspan=\"1\" rowspan=\"1\" colwidth=\"316\"><p data-block-id=\"2a7800a0-08a0-4a4e-b853-a8e9ab33ecf7\">15 minutos</p></td><td colspan=\"1\" rowspan=\"1\" colwidth=\"316\"><p data-block-id=\"b8607f84-a141-4900-9b91-843b1dbb4246\">Mismo Día</p></td></tr><tr><td colspan=\"1\" rowspan=\"1\" colwidth=\"316\"><p data-block-id=\"aaa3529a-0e88-40ad-94bc-2e2618fd5094\">Hora Límite</p></td><td colspan=\"1\" rowspan=\"1\" colwidth=\"316\"><p data-block-id=\"3f1f6a57-7f89-45c2-839d-a8d96f406ac1\">N/A</p></td><td colspan=\"1\" rowspan=\"1\" colwidth=\"316\"><p data-block-id=\"aa1cbfe7-5805-45f2-b0f2-b6820707efa4\">14:00 GMT+7</p></td></tr><tr><td colspan=\"1\" rowspan=\"1\" colwidth=\"316\"><p data-block-id=\"0dc221e0-31e5-40c6-b34e-cfb4561ce9b0\">Límite de Transacción</p></td><td colspan=\"1\" rowspan=\"1\" colwidth=\"316\"><p data-block-id=\"a51c7e2a-9356-4752-aefe-3d424e870aa7\">250,000,000</p></td><td colspan=\"1\" rowspan=\"1\" colwidth=\"316\"><p data-block-id=\"c7cc5402-1eec-4908-a809-08c7de65390f\">Ilimitado</p></td></tr><tr><td colspan=\"1\" rowspan=\"1\" colwidth=\"316\"><p data-block-id=\"15da2347-b5e2-459c-81bf-c1c2efadc5e9\">Soporte de Descripción</p></td><td colspan=\"1\" rowspan=\"1\" colwidth=\"316\"><p data-block-id=\"83ec00f0-fac3-460d-b550-3f7efe973029\">No</p></td><td colspan=\"1\" rowspan=\"1\" colwidth=\"316\"><p data-block-id=\"22668692-b6e0-4255-acba-8fea1e808ee2\">No</p></td></tr><tr><td colspan=\"1\" rowspan=\"1\" colwidth=\"316\"><p data-block-id=\"e6aa451a-2f43-4e3a-ae85-f5b8184a1495\">Caso de Uso Compatible</p></td><td colspan=\"1\" rowspan=\"1\" colwidth=\"316\"><p data-block-id=\"0664b24b-fd31-476e-a5b3-8f4045eeccb7\">Payout, Cross-Border Payout, Payout Link</p></td><td colspan=\"1\" rowspan=\"1\" colwidth=\"316\"><p data-block-id=\"ea29dea1-35c2-42b2-be02-5988f38d594c\">Payout, Cross-Border Payout, Payout Link</p></td></tr></tbody></table></div><p data-block-id=\"6e7615e0-9fa8-4682-906a-f2dbf515ba66\"><em>*Requiere activación. Póngase en contacto con help@xendit.co para activar.</em></p><h2 data-block-id=\"7ae25833-1a45-4534-8566-fc8d06501a1e\">Códigos de canal</h2><p data-block-id=\"1ff5713a-e672-4fa4-af2a-f5a48571b5fc\">Conozca los diferentes destinos de Payout que admitimos junto con su información específica de destino en la siguiente tabla:</p><p data-block-id=\"8af27fed-1dcd-416c-accd-ecef8c9cde3f\"><iframe src=\"https://airtable.com/embed/appYc7UnQq5CmKe0G/shrKTJKY9DD45nq2i?viewControls=on\" frameborder=\"0\" allowfullscreen=\"true\" allow=\"accelerometer; autoplay; clipboard-write; encrypted-media; gyroscope; picture-in-picture\" title style=\"background:transparent;border:1px solid #ccc;width:100%;height:533px;display:flex;margin-right:auto;\" width=\"100%\" height=\"533\" onmousewheel></iframe></p><p data-block-id=\"165b5698-9657-4f6f-9219-6bf7ec19d301\"></p><h2 data-block-id=\"9ef535f3-07c9-462f-a7c4-7c6cadc264ac\">Valores Requeridos (Para Cross Border Payouts)</h2><p data-block-id=\"e3e8f0c6-aaea-4305-b5f6-c729a4fea3f2\">Como requisito previo para crear un Cross Border Payout, se le solicita que nos envíe la información del remitente y del destinatario final. Conozca la información requerida para la región para comenzar a enviar Payouts:</p><h3 data-block-id=\"f9c1c378-1df8-42bc-9910-5ab16f56b3b1\">Remitente</h3><div data-type=\"table-content\"><table width=\"948\" class=\"editor360-table\" borderstyle=\"solid\" style=\"max-width:948px;width:948px;\"><colgroup><col style=\"width:316px;\"><col style=\"width:316px;\"><col style=\"width:316px;\"></colgroup><tbody><tr><th colspan=\"1\" rowspan=\"1\" colwidth=\"316\"><p data-block-id=\"2dea98bb-82b9-44d8-ba1e-1e72a2e60c65\">Parámetro de Campo</p></th><th colspan=\"1\" rowspan=\"1\" colwidth=\"316\"><p data-block-id=\"96028edf-d5fe-4aa6-87e1-c48746354822\">Tipo</p></th><th colspan=\"1\" rowspan=\"1\" colwidth=\"316\"><p data-block-id=\"48b85d69-8943-419a-ab7a-39e0883e9173\">Descripción</p></th></tr><tr><td colspan=\"1\" rowspan=\"1\" colwidth=\"316\" style=\"vertical-align:middle;box-sizing:border-box;padding:10px;\"><p data-block-id=\"e4d8aa8e-f7f6-4f11-b61e-c014d82e3465\"><code>first_name</code></p></td><td colspan=\"1\" rowspan=\"1\" colwidth=\"316\"><p data-block-id=\"ccab8e1a-acd6-4f4b-8de6-02d58260793b\"><code>INDIVIDUAL</code></p></td><td colspan=\"1\" rowspan=\"1\" colwidth=\"316\" style=\"box-sizing:border-box;padding:10px;vertical-align:top;\"><p data-block-id=\"8a2d881d-a15f-48a6-ba74-318274878f60\">Nombre del remitente</p></td></tr><tr><td colspan=\"1\" rowspan=\"1\" colwidth=\"316\" style=\"vertical-align:middle;box-sizing:border-box;padding:10px;\"><p data-block-id=\"8f6b72e4-3957-4586-b069-2995e01521ee\"><code>last_name</code></p></td><td colspan=\"1\" rowspan=\"1\" colwidth=\"316\"><p data-block-id=\"739ec33f-d34c-4e53-a5b1-1e1143fac00f\"><code>INDIVIDUAL</code></p></td><td colspan=\"1\" rowspan=\"1\" colwidth=\"316\" style=\"box-sizing:border-box;padding:10px;vertical-align:top;\"><p data-block-id=\"70683a7f-d642-4b5f-8a0b-05341a7cf49a\">Apellido del remitente</p></td></tr><tr><td colspan=\"1\" rowspan=\"1\" colwidth=\"316\"><p data-block-id=\"e94998e1-86de-493a-9c58-ec766926fca2\"><code>business_name</code></p></td><td colspan=\"1\" rowspan=\"1\" colwidth=\"316\"><p data-block-id=\"4ac71789-7f47-4be4-86ae-c37e0701df84\"><code>BUSINESS</code></p></td><td colspan=\"1\" rowspan=\"1\" colwidth=\"316\" style=\"box-sizing:border-box;padding:10px;vertical-align:top;\"><p data-block-id=\"d307563d-5bd4-4cf3-b814-a8fc2e35b9d1\">Nombre completo registrado del remitente</p></td></tr></tbody></table></div><p data-block-id=\"1491a0dd-d239-4440-a9e0-785b37ffc0b3\"></p><h3 data-block-id=\"a94aeee5-d7ca-41d9-832a-c26744f93aaf\">Destinatario</h3><div data-type=\"table-content\"><table width=\"948\" class=\"editor360-table\" borderstyle=\"solid\" style=\"max-width:948px;width:948px;\"><colgroup><col style=\"width:316px;\"><col style=\"width:316px;\"><col style=\"width:316px;\"></colgroup><tbody><tr><th colspan=\"1\" rowspan=\"1\" colwidth=\"316\"><p data-block-id=\"42269971-6ddd-41de-b872-2d1d7dfe8a5a\">Parámetro de Campo</p></th><th colspan=\"1\" rowspan=\"1\" colwidth=\"316\"><p data-block-id=\"b58f2415-8361-45f5-a06d-e2267c81f78c\">Tipo</p></th><th colspan=\"1\" rowspan=\"1\" colwidth=\"316\"><p data-block-id=\"0595f7e6-463b-42de-8000-5cf48d44ac2a\">Descripción</p></th></tr><tr><td colspan=\"1\" rowspan=\"1\" colwidth=\"316\" style=\"vertical-align:middle;box-sizing:border-box;padding:10px;\"><p data-block-id=\"23b4dfad-06c8-467d-a369-5038efffa375\"><code>first_name</code></p></td><td colspan=\"1\" rowspan=\"1\" colwidth=\"316\"><p data-block-id=\"5e3de2cf-74eb-45ed-a2e5-54136513ab92\"><code>INDIVIDUAL</code></p></td><td colspan=\"1\" rowspan=\"1\" colwidth=\"316\" style=\"box-sizing:border-box;padding:10px;vertical-align:top;\"><p data-block-id=\"d339a321-3d87-4381-abd2-d64364126a94\">Nombre del destinatario</p></td></tr><tr><td colspan=\"1\" rowspan=\"1\" colwidth=\"316\" style=\"vertical-align:middle;box-sizing:border-box;padding:10px;\"><p data-block-id=\"ad5fd060-35db-4ccc-b3c6-352dcc8841b3\"><code>last_name</code></p></td><td colspan=\"1\" rowspan=\"1\" colwidth=\"316\"><p data-block-id=\"e531b009-eef3-44da-ad1e-f61dde6571eb\"><code>INDIVIDUAL</code></p></td><td colspan=\"1\" rowspan=\"1\" colwidth=\"316\" style=\"box-sizing:border-box;padding:10px;vertical-align:top;\"><p data-block-id=\"179b7c54-f42a-491c-8a11-2585aa854342\">Apellido del destinatario</p></td></tr><tr><td colspan=\"1\" rowspan=\"1\" colwidth=\"316\"><p data-block-id=\"e4b88d37-d942-47ad-ab65-1ad9c2f36b43\"><code>business_name</code></p></td><td colspan=\"1\" rowspan=\"1\" colwidth=\"316\"><p data-block-id=\"79a70831-46d4-4886-a7a1-09c78ba2f6c2\"><code>BUSINESS</code></p></td><td colspan=\"1\" rowspan=\"1\" colwidth=\"316\" style=\"box-sizing:border-box;padding:10px;vertical-align:top;\"><p data-block-id=\"20c947e9-b84f-4391-a8a2-488ad68945c1\">Nombre completo registrado del destinatario</p></td></tr><tr><td colspan=\"1\" rowspan=\"1\" colwidth=\"316\" style=\"box-sizing:border-box;padding:10px;vertical-align:top;\"><p data-block-id=\"bbed3e7b-c700-48c7-bbcb-5c0bee0fac29\"><code>company</code></p></td><td colspan=\"1\" rowspan=\"1\" colwidth=\"316\" style=\"box-sizing:border-box;padding:10px;vertical-align:top;\"><p data-block-id=\"1f0c7be5-df81-4d96-995c-0a983b371a6f\">Cualquiera</p></td><td colspan=\"1\" rowspan=\"1\" colwidth=\"316\" style=\"box-sizing:border-box;padding:10px;vertical-align:top;\"><p data-block-id=\"3587edb1-dcdb-4771-bb6f-97b91f2ed95e\">Código de canal de la cuenta del destinatario</p></td></tr><tr><td colspan=\"1\" rowspan=\"1\" colwidth=\"316\" style=\"box-sizing:border-box;padding:10px;vertical-align:top;\"><p data-block-id=\"5e4d95d7-32b7-48f0-8294-16401b15fa48\"><code>account_number</code></p></td><td colspan=\"1\" rowspan=\"1\" colwidth=\"316\" style=\"box-sizing:border-box;padding:10px;vertical-align:top;\"><p data-block-id=\"96660eb6-1cc8-4571-aedc-820c49158ef1\">Cualquiera</p></td><td colspan=\"1\" rowspan=\"1\" colwidth=\"316\" style=\"box-sizing:border-box;padding:10px;vertical-align:top;\"><p data-block-id=\"df44dab6-aabb-4ec0-a931-5f422224244f\">Número de cuenta del detalle de la cuenta del destinatario</p></td></tr><tr><td colspan=\"1\" rowspan=\"1\" colwidth=\"316\"><p data-block-id=\"5ce0bfa2-25d9-4ed7-bfe2-3af9dc7a586d\"><code>account_holder_name</code></p></td><td colspan=\"1\" rowspan=\"1\" colwidth=\"316\" style=\"box-sizing:border-box;padding:10px;vertical-align:top;\"><p data-block-id=\"a4a2da7f-5976-4140-b265-f2e3d023f900\">Cualquiera</p></td><td colspan=\"1\" rowspan=\"1\" colwidth=\"316\"><p data-block-id=\"acbb63bf-dd76-4dff-8cba-7e43a253de2e\">Nombre del titular de la cuenta del detalle de la cuenta del destinatario</p></td></tr></tbody></table></div><p data-block-id=\"a5f4e0e1-5934-430e-826b-509b4142bcf3\"></p>","SeoTitle":"Vietnam","Description":null}]